CONTRIBUTING.rst
LICENSE
MANIFEST.in
README.rst
setup.cfg
setup.py
docs/Makefile
docs/authors.rst
docs/conf.py
docs/contributing.rst
docs/history.rst
docs/index.rst
docs/installation.rst
docs/make.bat
docs/modules.rst
docs/pychromatic.rst
docs/readme.rst
docs/usage.rst
docs/colors/color_tests.rst
docs/colors/output_2_0.png
docs/colors/output_2_1.png
docs/colors/output_2_10.png
docs/colors/output_2_11.png
docs/colors/output_2_12.png
docs/colors/output_2_13.png
docs/colors/output_2_14.png
docs/colors/output_2_15.png
docs/colors/output_2_2.png
docs/colors/output_2_3.png
docs/colors/output_2_4.png
docs/colors/output_2_5.png
docs/colors/output_2_6.png
docs/colors/output_2_7.png
docs/colors/output_2_8.png
docs/colors/output_2_9.png
pychromatic/__init__.py
pychromatic/colorclass.py
pychromatic/colors.py
pychromatic/cutils.py
pychromatic/decors.py
pychromatic/palette.py
pychromatic/plutils.py
pychromatic.egg-info/PKG-INFO
pychromatic.egg-info/SOURCES.txt
pychromatic.egg-info/dependency_links.txt
pychromatic.egg-info/not-zip-safe
pychromatic.egg-info/requires.txt
pychromatic.egg-info/top_level.txt
tests/__init__.py
tests/test_pychromatic.py