Metadata-Version: 2.1
Name: pychromatic
Version: 0.5.14
Summary: a pretty color selector for python
Home-page: https://github.com/srmnitc/pychromatic
Author: Sarath Menon, Abril Azocar Guzman
Author-email: sarathmenon@mailbox.org
License: GNU General Public License v3
Keywords: pychromatic
Platform: UNKNOWN
Classifier: Development Status :: 2 - Pre-Alpha
Classifier: Intended Audience :: Developers
Classifier: License :: OSI Approved :: GNU General Public License v3 (GPLv3)
Classifier: Natural Language :: English
Classifier: Programming Language :: Python :: 2
Classifier: Programming Language :: Python :: 2.7
Classifier: Programming Language :: Python :: 3
Classifier: Programming Language :: Python :: 3.5
Classifier: Programming Language :: Python :: 3.6
Classifier: Programming Language :: Python :: 3.7
Requires-Python: >=2.7, !=3.0.*, !=3.1.*, !=3.2.*, !=3.3.*, !=3.4.*
